RPCLayout/RPCLayout.py
RPCLayout/__init__.py
RPCLayout/__test__.py
RPCLayout/example.py
RPCLayout-2.1.3.dist-info/LICENSE
RPCLayout-2.1.3.dist-info/METADATA
RPCLayout-2.1.3.dist-info/WHEEL
RPCLayout-2.1.3.dist-info/top_level.txt
RPCLayout-2.1.3.dist-info/zip-safe
RPCLayout-2.1.3.dist-info/RECORD
