Metadata-Version: 2.1
Name: RPCLayout
Version: 2.1.3
Summary: Simple template API for Discord rich presence!
Home-page: https://github.com/neopkr/RPCLayout
Author: neokeee
Author-email: neopkr90@gmail.com
License: MIT
Project-URL: Bug Tracker, https://github.com/neopkr/RPCLayout/issues
Platform: Windows
Platform: OSX
Classifier: Programming Language :: Python :: 3
Classifier: License :: OSI Approved :: MIT License
Classifier: Operating System :: OS Independent
Requires-Python: >=3.5
License-File: LICENSE
